aws_connect_cli/__init__.py
aws_connect_cli/main.py
aws_connect_cli/services/__init__.py
aws_connect_cli/services/billing.py
aws_connect_cli/services/ec2.py
aws_connect_cli/services/login.py
aws_connect_cli/services/s3.py
aws_connect_cli-0.2.7.dist-info/METADATA
aws_connect_cli-0.2.7.dist-info/WHEEL
aws_connect_cli-0.2.7.dist-info/entry_points.txt
aws_connect_cli-0.2.7.dist-info/top_level.txt
aws_connect_cli-0.2.7.dist-info/RECORD
