Metadata-Version: 2.2
Name: aws-connect-cli
Version: 0.2.7
Summary: A CLI tool to manage AWS services
Author-email: Jayasurya A <techie4coffee@gmail.com>
License: MIT
Requires-Python: >=3.11
Requires-Dist: boto3>=1.36.26
Requires-Dist: inquirer>=3.4.0
Requires-Dist: inquirerpy>=0.3.4
Requires-Dist: rich>=13.9.4
Requires-Dist: tabulate>=0.9.0
Requires-Dist: typer>=0.15.1
